ThePerformanceOfOpenSourceApplications/README.md
ThePerformanceOfOpenSourceApplications/__init__.py
ThePerformanceOfOpenSourceApplications/__main__.py
ThePerformanceOfOpenSourceApplications/file.epub
ThePerformanceOfOpenSourceApplications/index.html
ThePerformanceOfOpenSourceApplications/css/__init__.py
ThePerformanceOfOpenSourceApplications/css/annotations.css
ThePerformanceOfOpenSourceApplications/css/main.css
ThePerformanceOfOpenSourceApplications/css/normalize.css
ThePerformanceOfOpenSourceApplications/css/popup.css
ThePerformanceOfOpenSourceApplications/font/__init__.py
ThePerformanceOfOpenSourceApplications/font/fontello.eot
ThePerformanceOfOpenSourceApplications/font/fontello.svg
ThePerformanceOfOpenSourceApplications/font/fontello.ttf
ThePerformanceOfOpenSourceApplications/font/fontello.woff
ThePerformanceOfOpenSourceApplications/img/__init__.py
ThePerformanceOfOpenSourceApplications/img/annotator-glyph-sprite.png
ThePerformanceOfOpenSourceApplications/img/annotator-icon-sprite.png
ThePerformanceOfOpenSourceApplications/img/apple-touch-icon.png
ThePerformanceOfOpenSourceApplications/img/cancelfullscreen.png
ThePerformanceOfOpenSourceApplications/img/close.png
ThePerformanceOfOpenSourceApplications/img/fullscreen.png
ThePerformanceOfOpenSourceApplications/img/loader.gif
ThePerformanceOfOpenSourceApplications/img/menu-icon.png
ThePerformanceOfOpenSourceApplications/img/save.png
ThePerformanceOfOpenSourceApplications/img/saved.png
ThePerformanceOfOpenSourceApplications/img/settings-s.png
ThePerformanceOfOpenSourceApplications/img/settings.png
ThePerformanceOfOpenSourceApplications/img/star.png
ThePerformanceOfOpenSourceApplications/js/__init__.py
ThePerformanceOfOpenSourceApplications/js/epub.js
ThePerformanceOfOpenSourceApplications/js/epub.min.js
ThePerformanceOfOpenSourceApplications/js/epub.min.map
ThePerformanceOfOpenSourceApplications/js/hooks.min.js
ThePerformanceOfOpenSourceApplications/js/hooks.min.map
the_performance_of_open_source_applications-2024.3.2.0.dist-info/METADATA
the_performance_of_open_source_applications-2024.3.2.0.dist-info/WHEEL
the_performance_of_open_source_applications-2024.3.2.0.dist-info/entry_points.txt
the_performance_of_open_source_applications-2024.3.2.0.dist-info/top_level.txt
the_performance_of_open_source_applications-2024.3.2.0.dist-info/RECORD
